LICENSE
README.md
setup.py
test_RAG_X/__init__.py
test_RAG_X/document_extractor.py
test_RAG_X/evaluation_question_generator.py
test_RAG_X/hub.py
test_RAG_X/library_exceptions.py
test_RAG_X/text_chunker.py
test_RAG_X/text_cleaner.py
test_RAG_X/text_utils.py
test_RAG_X/tru_lens_evaluator.py
test_RAG_X.egg-info/PKG-INFO
test_RAG_X.egg-info/SOURCES.txt
test_RAG_X.egg-info/dependency_links.txt
test_RAG_X.egg-info/requires.txt
test_RAG_X.egg-info/top_level.txt