Metadata-Version: 2.1
Name: test_RAG_X
Version: 0.2.1
Summary: This library is to search the best parameters across different steps of the RAG process.
Home-page: https://github.com/hidevscommunity/gen-ai-library/tree/main/Ankit
Author: Ankit
Author-email: a.baliyan008@gmail.com
License: MIT
Classifier: License :: OSI Approved :: MIT License
Classifier: Programming Language :: Python :: 3.7
Classifier: Programming Language :: Python :: 3.8
Classifier: Programming Language :: Python :: 3.9
Classifier: Programming Language :: Python :: 3.10
License-File: LICENSE
Requires-Dist: langchain>=0.1.13
Requires-Dist: langchain-openai>=0.1.1
Requires-Dist: trulens-eval>=0.27.0
Requires-Dist: chromadb>=0.4.24
Requires-Dist: sentence-transformers>=2.6.1
Requires-Dist: unstructured[pdf]==0.13.0
